SoftwareAnalysisAndDesignILectureNotesCunyCsci135/README.md
SoftwareAnalysisAndDesignILectureNotesCunyCsci135/__init__.py
SoftwareAnalysisAndDesignILectureNotesCunyCsci135/__main__.py
SoftwareAnalysisAndDesignILectureNotesCunyCsci135/file.pdf
SoftwareAnalysisAndDesignILectureNotesCunyCsci135/index.html
software_analysis_and_design_i_lecture_notes_cuny_csci135-2024.3.2.0.dist-info/METADATA
software_analysis_and_design_i_lecture_notes_cuny_csci135-2024.3.2.0.dist-info/WHEEL
software_analysis_and_design_i_lecture_notes_cuny_csci135-2024.3.2.0.dist-info/entry_points.txt
software_analysis_and_design_i_lecture_notes_cuny_csci135-2024.3.2.0.dist-info/top_level.txt
software_analysis_and_design_i_lecture_notes_cuny_csci135-2024.3.2.0.dist-info/RECORD
